swampymud/__init__.py
swampymud/__main__.py
swampymud/_types.py
swampymud/character.py
swampymud/entity.py
swampymud/inventory.py
swampymud/item.py
swampymud/location.py
swampymud/mudscript.py
swampymud/mudserver.py
swampymud/world.py
swampymud/util/__init__.py
swampymud/util/biject.py
swampymud/util/color.py
swampymud/util/english.py
swampymud/util/misc.py
swampymud/util/parser.py
swampymud/util/shadowdict.py
swampymud/util/validate.py
tests/__init__.py
tests/test_character.py
tests/test_entity.py
tests/test_interaction.py
tests/test_inventory.py
tests/test_item.py
tests/test_location.py
tests/test_mudscript.py
tests/test_util_biiject.py
tests/test_util_color.py
tests/test_util_misc.py
tests/test_util_parser.py
tests/test_util_shadowdict.py
tests/test_util_validate.py
tests/test_world.py
swampymud-0.2.0.dist-info/LICENSE.md
swampymud-0.2.0.dist-info/METADATA
swampymud-0.2.0.dist-info/WHEEL
swampymud-0.2.0.dist-info/top_level.txt
swampymud-0.2.0.dist-info/RECORD
