Metadata-Version: 2.1
Name: swampymud
Version: 0.2.0
Summary: Create multi-user dungeons (MUDs) and RPGs with telnet / WebSockets.
Home-page: https://swampymud.net
Author: The UF Open Source Club
Author-email: will@ovvens.com
License: UNKNOWN
Platform: UNKNOWN
Classifier: Development Status :: 3 - Alpha
Classifier: Environment :: Console
Classifier: License :: OSI Approved :: MIT License
Classifier: Operating System :: OS Independent
Classifier: Programming Language :: Python :: 3 :: Only
Classifier: Programming Language :: Python :: 3.6
Classifier: Programming Language :: Python :: 3.7
Classifier: Programming Language :: Python :: 3.8
Classifier: Programming Language :: Python :: 3.9
Classifier: Topic :: Games/Entertainment
Classifier: Topic :: Games/Entertainment :: Multi-User Dungeons (MUD)
Classifier: Intended Audience :: Developers
Classifier: Intended Audience :: Education
Requires-Python: >=3.6
Requires-Dist: websockets
Requires-Dist: PyYaml
